.gitignore
README.md
setup.py
tests/test_jenkins_jobs.py
zops/__init__.py
zops.jenkins_jobs.egg-info/PKG-INFO
zops.jenkins_jobs.egg-info/SOURCES.txt
zops.jenkins_jobs.egg-info/dependency_links.txt
zops.jenkins_jobs.egg-info/entry_points.txt
zops.jenkins_jobs.egg-info/namespace_packages.txt
zops.jenkins_jobs.egg-info/requires.txt
zops.jenkins_jobs.egg-info/top_level.txt
zops/jenkins_jobs/__init__.py
zops/jenkins_jobs/cli.py