Metadata-Version: 1.1
Name: zops.jenkins-jobs
Version: 0.5.0
Summary: Manage the creation of jenkins jobs.
Home-page: https://github.com/zerotk/zops.jenkins_jobs
Author: Alexandre Andrade
Author-email: kaniabi@gmail.com
License: MIT license
Keywords: development environment,shell,operations
Platform: UNKNOWN
Classifier: Development Status :: 2 - Pre-Alpha
Classifier: Intended Audience :: Developers
Classifier: License :: OSI Approved :: MIT License
Classifier: Natural Language :: English
Classifier: Programming Language :: Python :: 2
Classifier: Programming Language :: Python :: 2.7
Classifier: Programming Language :: Python :: 3
Classifier: Programming Language :: Python :: 3.5
